{
  "apiVersion": "2026-01-01-preview",
  "emitterVersion": "0.48.0",
  "crossLanguageDefinitions": {
    "CrossLanguagePackageId": "Microsoft.DBforPostgreSQL",
    "CrossLanguageDefinitionId": {
      "@azure/arm-postgresql-flexible!OperationList:interface": "Microsoft.DBforPostgreSQL.OperationList",
      "@azure/arm-postgresql-flexible!Operation:interface": "Microsoft.DBforPostgreSQL.Operation",
      "@azure/arm-postgresql-flexible!OperationDisplay:interface": "Microsoft.DBforPostgreSQL.OperationDisplay",
      "@azure/arm-postgresql-flexible!ErrorResponse:interface": "Azure.ResourceManager.CommonTypes.ErrorResponse",
      "@azure/arm-postgresql-flexible!ErrorDetail:interface": "Azure.ResourceManager.CommonTypes.ErrorDetail",
      "@azure/arm-postgresql-flexible!ErrorAdditionalInfo:interface": "Azure.ResourceManager.CommonTypes.ErrorAdditionalInfo",
      "@azure/arm-postgresql-flexible!Migration:interface": "Microsoft.DBforPostgreSQL.Migration",
      "@azure/arm-postgresql-flexible!MigrationProperties:interface": "Microsoft.DBforPostgreSQL.MigrationProperties",
      "@azure/arm-postgresql-flexible!MigrationStatus:interface": "Microsoft.DBforPostgreSQL.MigrationStatus",
      "@azure/arm-postgresql-flexible!MigrationSubstateDetails:interface": "Microsoft.DBforPostgreSQL.MigrationSubstateDetails",
      "@azure/arm-postgresql-flexible!DatabaseMigrationState:interface": "Microsoft.DBforPostgreSQL.DatabaseMigrationState",
      "@azure/arm-postgresql-flexible!ValidationDetails:interface": "Microsoft.DBforPostgreSQL.ValidationDetails",
      "@azure/arm-postgresql-flexible!ValidationSummaryItem:interface": "Microsoft.DBforPostgreSQL.ValidationSummaryItem",
      "@azure/arm-postgresql-flexible!ValidationMessage:interface": "Microsoft.DBforPostgreSQL.ValidationMessage",
      "@azure/arm-postgresql-flexible!DbLevelValidationStatus:interface": "Microsoft.DBforPostgreSQL.DbLevelValidationStatus",
      "@azure/arm-postgresql-flexible!DbServerMetadata:interface": "Microsoft.DBforPostgreSQL.DbServerMetadata",
      "@azure/arm-postgresql-flexible!ServerSku:interface": "Microsoft.DBforPostgreSQL.ServerSku",
      "@azure/arm-postgresql-flexible!MigrationSecretParameters:interface": "Microsoft.DBforPostgreSQL.MigrationSecretParameters",
      "@azure/arm-postgresql-flexible!AdminCredentials:interface": "Microsoft.DBforPostgreSQL.AdminCredentials",
      "@azure/arm-postgresql-flexible!TrackedResource:interface": "Azure.ResourceManager.CommonTypes.TrackedResource",
      "@azure/arm-postgresql-flexible!Resource:interface": "Azure.ResourceManager.CommonTypes.Resource",
      "@azure/arm-postgresql-flexible!SystemData:interface": "Azure.ResourceManager.CommonTypes.SystemData",
      "@azure/arm-postgresql-flexible!MigrationResourceForPatch:interface": "Microsoft.DBforPostgreSQL.MigrationResourceForPatch",
      "@azure/arm-postgresql-flexible!MigrationPropertiesForPatch:interface": "Microsoft.DBforPostgreSQL.MigrationPropertiesForPatch",
      "@azure/arm-postgresql-flexible!MigrationSecretParametersForPatch:interface": "Microsoft.DBforPostgreSQL.MigrationSecretParametersForPatch",
      "@azure/arm-postgresql-flexible!AdminCredentialsForPatch:interface": "Microsoft.DBforPostgreSQL.AdminCredentialsForPatch",
      "@azure/arm-postgresql-flexible!MigrationList:interface": "Microsoft.DBforPostgreSQL.MigrationList",
      "@azure/arm-postgresql-flexible!MigrationNameAvailability:interface": "Microsoft.DBforPostgreSQL.MigrationNameAvailability",
      "@azure/arm-postgresql-flexible!Server:interface": "Microsoft.DBforPostgreSQL.Server",
      "@azure/arm-postgresql-flexible!ServerProperties:interface": "Microsoft.DBforPostgreSQL.ServerProperties",
      "@azure/arm-postgresql-flexible!Storage:interface": "Microsoft.DBforPostgreSQL.Storage",
      "@azure/arm-postgresql-flexible!AuthConfig:interface": "Microsoft.DBforPostgreSQL.AuthConfig",
      "@azure/arm-postgresql-flexible!DataEncryption:interface": "Microsoft.DBforPostgreSQL.DataEncryption",
      "@azure/arm-postgresql-flexible!Backup:interface": "Microsoft.DBforPostgreSQL.Backup",
      "@azure/arm-postgresql-flexible!Network:interface": "Microsoft.DBforPostgreSQL.Network",
      "@azure/arm-postgresql-flexible!HighAvailability:interface": "Microsoft.DBforPostgreSQL.HighAvailability",
      "@azure/arm-postgresql-flexible!MaintenanceWindow:interface": "Microsoft.DBforPostgreSQL.MaintenanceWindow",
      "@azure/arm-postgresql-flexible!Replica:interface": "Microsoft.DBforPostgreSQL.Replica",
      "@azure/arm-postgresql-flexible!PrivateEndpointConnection:interface": "Microsoft.DBforPostgreSQL.PrivateEndpointConnection",
      "@azure/arm-postgresql-flexible!PrivateEndpointConnectionProperties:interface": "Azure.ResourceManager.CommonTypes.PrivateEndpointConnectionProperties",
      "@azure/arm-postgresql-flexible!PrivateEndpoint:interface": "Azure.ResourceManager.CommonTypes.PrivateEndpoint",
      "@azure/arm-postgresql-flexible!PrivateLinkServiceConnectionState:interface": "Azure.ResourceManager.CommonTypes.PrivateLinkServiceConnectionState",
      "@azure/arm-postgresql-flexible!Cluster:interface": "Microsoft.DBforPostgreSQL.Cluster",
      "@azure/arm-postgresql-flexible!Sku:interface": "Microsoft.DBforPostgreSQL.Sku",
      "@azure/arm-postgresql-flexible!UserAssignedIdentity:interface": "Microsoft.DBforPostgreSQL.UserAssignedIdentity",
      "@azure/arm-postgresql-flexible!UserIdentity:interface": "Microsoft.DBforPostgreSQL.UserIdentity",
      "@azure/arm-postgresql-flexible!ArmOperationStatusResourceProvisioningState:interface": "Azure.ResourceManager.ArmOperationStatus",
      "@azure/arm-postgresql-flexible!ServerForPatch:interface": "Microsoft.DBforPostgreSQL.ServerForPatch",
      "@azure/arm-postgresql-flexible!SkuForPatch:interface": "Microsoft.DBforPostgreSQL.SkuForPatch",
      "@azure/arm-postgresql-flexible!ServerPropertiesForPatch:interface": "Microsoft.DBforPostgreSQL.ServerPropertiesForPatch",
      "@azure/arm-postgresql-flexible!BackupForPatch:interface": "Microsoft.DBforPostgreSQL.BackupForPatch",
      "@azure/arm-postgresql-flexible!HighAvailabilityForPatch:interface": "Microsoft.DBforPostgreSQL.HighAvailabilityForPatch",
      "@azure/arm-postgresql-flexible!MaintenanceWindowForPatch:interface": "Microsoft.DBforPostgreSQL.MaintenanceWindowForPatch",
      "@azure/arm-postgresql-flexible!AuthConfigForPatch:interface": "Microsoft.DBforPostgreSQL.AuthConfigForPatch",
      "@azure/arm-postgresql-flexible!ServerList:interface": "Microsoft.DBforPostgreSQL.ServerList",
      "@azure/arm-postgresql-flexible!RestartParameter:interface": "Microsoft.DBforPostgreSQL.RestartParameter",
      "@azure/arm-postgresql-flexible!MigrateNetworkStatus:interface": "Microsoft.DBforPostgreSQL.MigrateNetworkStatus",
      "@azure/arm-postgresql-flexible!Configuration:interface": "Microsoft.DBforPostgreSQL.Configuration",
      "@azure/arm-postgresql-flexible!ConfigurationProperties:interface": "Microsoft.DBforPostgreSQL.ConfigurationProperties",
      "@azure/arm-postgresql-flexible!ProxyResource:interface": "Azure.ResourceManager.CommonTypes.ProxyResource",
      "@azure/arm-postgresql-flexible!ConfigurationForUpdate:interface": "Microsoft.DBforPostgreSQL.ConfigurationForUpdate",
      "@azure/arm-postgresql-flexible!ConfigurationList:interface": "Microsoft.DBforPostgreSQL.ConfigurationList",
      "@azure/arm-postgresql-flexible!Database:interface": "Microsoft.DBforPostgreSQL.Database",
      "@azure/arm-postgresql-flexible!DatabaseProperties:interface": "Microsoft.DBforPostgreSQL.DatabaseProperties",
      "@azure/arm-postgresql-flexible!DatabaseList:interface": "Microsoft.DBforPostgreSQL.DatabaseList",
      "@azure/arm-postgresql-flexible!FirewallRule:interface": "Microsoft.DBforPostgreSQL.FirewallRule",
      "@azure/arm-postgresql-flexible!FirewallRuleProperties:interface": "Microsoft.DBforPostgreSQL.FirewallRuleProperties",
      "@azure/arm-postgresql-flexible!FirewallRuleList:interface": "Microsoft.DBforPostgreSQL.FirewallRuleList",
      "@azure/arm-postgresql-flexible!PrivateEndpointConnectionList:interface": "Microsoft.DBforPostgreSQL.PrivateEndpointConnectionList",
      "@azure/arm-postgresql-flexible!PrivateLinkResource:interface": "Microsoft.DBforPostgreSQL.PrivateLinkResource",
      "@azure/arm-postgresql-flexible!PrivateLinkResourceProperties:interface": "Azure.ResourceManager.CommonTypes.PrivateLinkResourceProperties",
      "@azure/arm-postgresql-flexible!PrivateLinkResourceList:interface": "Microsoft.DBforPostgreSQL.PrivateLinkResourceList",
      "@azure/arm-postgresql-flexible!VirtualEndpoint:interface": "Microsoft.DBforPostgreSQL.VirtualEndpoint",
      "@azure/arm-postgresql-flexible!VirtualEndpointResourceProperties:interface": "Microsoft.DBforPostgreSQL.VirtualEndpointResourceProperties",
      "@azure/arm-postgresql-flexible!VirtualEndpointResourceForPatch:interface": "Microsoft.DBforPostgreSQL.VirtualEndpointResourceForPatch",
      "@azure/arm-postgresql-flexible!VirtualEndpointsList:interface": "Microsoft.DBforPostgreSQL.VirtualEndpointsList",
      "@azure/arm-postgresql-flexible!AdministratorMicrosoftEntra:interface": "Microsoft.DBforPostgreSQL.AdministratorMicrosoftEntra",
      "@azure/arm-postgresql-flexible!AdministratorMicrosoftEntraProperties:interface": "Microsoft.DBforPostgreSQL.AdministratorMicrosoftEntraProperties",
      "@azure/arm-postgresql-flexible!AdministratorMicrosoftEntraAdd:interface": "Microsoft.DBforPostgreSQL.AdministratorMicrosoftEntraAdd",
      "@azure/arm-postgresql-flexible!AdministratorMicrosoftEntraPropertiesForAdd:interface": "Microsoft.DBforPostgreSQL.AdministratorMicrosoftEntraPropertiesForAdd",
      "@azure/arm-postgresql-flexible!AdministratorMicrosoftEntraList:interface": "Microsoft.DBforPostgreSQL.AdministratorMicrosoftEntraList",
      "@azure/arm-postgresql-flexible!CapabilityList:interface": "Microsoft.DBforPostgreSQL.CapabilityList",
      "@azure/arm-postgresql-flexible!Capability:interface": "Microsoft.DBforPostgreSQL.Capability",
      "@azure/arm-postgresql-flexible!ServerEditionCapability:interface": "Microsoft.DBforPostgreSQL.ServerEditionCapability",
      "@azure/arm-postgresql-flexible!StorageEditionCapability:interface": "Microsoft.DBforPostgreSQL.StorageEditionCapability",
      "@azure/arm-postgresql-flexible!StorageMbCapability:interface": "Microsoft.DBforPostgreSQL.StorageMbCapability",
      "@azure/arm-postgresql-flexible!StorageTierCapability:interface": "Microsoft.DBforPostgreSQL.StorageTierCapability",
      "@azure/arm-postgresql-flexible!CapabilityBase:interface": "Microsoft.DBforPostgreSQL.CapabilityBase",
      "@azure/arm-postgresql-flexible!ServerSkuCapability:interface": "Microsoft.DBforPostgreSQL.ServerSkuCapability",
      "@azure/arm-postgresql-flexible!SupportedFeature:interface": "Microsoft.DBforPostgreSQL.SupportedFeature",
      "@azure/arm-postgresql-flexible!ServerVersionCapability:interface": "Microsoft.DBforPostgreSQL.ServerVersionCapability",
      "@azure/arm-postgresql-flexible!FastProvisioningEditionCapability:interface": "Microsoft.DBforPostgreSQL.FastProvisioningEditionCapability",
      "@azure/arm-postgresql-flexible!CapturedLogList:interface": "Microsoft.DBforPostgreSQL.CapturedLogList",
      "@azure/arm-postgresql-flexible!CapturedLog:interface": "Microsoft.DBforPostgreSQL.CapturedLog",
      "@azure/arm-postgresql-flexible!CapturedLogProperties:interface": "Microsoft.DBforPostgreSQL.CapturedLogProperties",
      "@azure/arm-postgresql-flexible!LtrPreBackupRequest:interface": "Microsoft.DBforPostgreSQL.LtrPreBackupRequest",
      "@azure/arm-postgresql-flexible!BackupRequestBase:interface": "Microsoft.DBforPostgreSQL.BackupRequestBase",
      "@azure/arm-postgresql-flexible!BackupSettings:interface": "Microsoft.DBforPostgreSQL.BackupSettings",
      "@azure/arm-postgresql-flexible!LtrPreBackupResponse:interface": "Microsoft.DBforPostgreSQL.LtrPreBackupResponse",
      "@azure/arm-postgresql-flexible!BackupsLongTermRetentionResponseProperties:interface": "Microsoft.DBforPostgreSQL.BackupsLongTermRetentionResponseProperties",
      "@azure/arm-postgresql-flexible!BackupsLongTermRetentionRequest:interface": "Microsoft.DBforPostgreSQL.BackupsLongTermRetentionRequest",
      "@azure/arm-postgresql-flexible!BackupStoreDetails:interface": "Microsoft.DBforPostgreSQL.BackupStoreDetails",
      "@azure/arm-postgresql-flexible!BackupsLongTermRetentionResponse:interface": "Microsoft.DBforPostgreSQL.BackupsLongTermRetentionResponse",
      "@azure/arm-postgresql-flexible!LtrBackupOperationResponseProperties:interface": "Microsoft.DBforPostgreSQL.LtrBackupOperationResponseProperties",
      "@azure/arm-postgresql-flexible!BackupsLongTermRetentionOperation:interface": "Microsoft.DBforPostgreSQL.BackupsLongTermRetentionOperation",
      "@azure/arm-postgresql-flexible!LtrServerBackupOperationList:interface": "Microsoft.DBforPostgreSQL.LtrServerBackupOperationList",
      "@azure/arm-postgresql-flexible!AdvancedThreatProtectionSettingsModel:interface": "Microsoft.DBforPostgreSQL.AdvancedThreatProtectionSettingsModel",
      "@azure/arm-postgresql-flexible!AdvancedThreatProtectionSettingsProperties:interface": "Microsoft.DBforPostgreSQL.AdvancedThreatProtectionSettingsProperties",
      "@azure/arm-postgresql-flexible!AdvancedThreatProtectionSettingsList:interface": "Microsoft.DBforPostgreSQL.AdvancedThreatProtectionSettingsList",
      "@azure/arm-postgresql-flexible!BackupAutomaticAndOnDemand:interface": "Microsoft.DBforPostgreSQL.BackupAutomaticAndOnDemand",
      "@azure/arm-postgresql-flexible!BackupAutomaticAndOnDemandProperties:interface": "Microsoft.DBforPostgreSQL.BackupAutomaticAndOnDemandProperties",
      "@azure/arm-postgresql-flexible!BackupAutomaticAndOnDemandList:interface": "Microsoft.DBforPostgreSQL.BackupAutomaticAndOnDemandList",
      "@azure/arm-postgresql-flexible!TuningOptions:interface": "Microsoft.DBforPostgreSQL.TuningOptions",
      "@azure/arm-postgresql-flexible!TuningOptionsList:interface": "Microsoft.DBforPostgreSQL.TuningOptionsList",
      "@azure/arm-postgresql-flexible!ObjectRecommendationList:interface": "Microsoft.DBforPostgreSQL.ObjectRecommendationList",
      "@azure/arm-postgresql-flexible!ObjectRecommendation:interface": "Microsoft.DBforPostgreSQL.ObjectRecommendation",
      "@azure/arm-postgresql-flexible!ObjectRecommendationProperties:interface": "Microsoft.DBforPostgreSQL.ObjectRecommendationProperties",
      "@azure/arm-postgresql-flexible!ObjectRecommendationPropertiesImplementationDetails:interface": "Microsoft.DBforPostgreSQL.ObjectRecommendationPropertiesImplementationDetails",
      "@azure/arm-postgresql-flexible!ObjectRecommendationPropertiesAnalyzedWorkload:interface": "Microsoft.DBforPostgreSQL.ObjectRecommendationPropertiesAnalyzedWorkload",
      "@azure/arm-postgresql-flexible!ImpactRecord:interface": "Microsoft.DBforPostgreSQL.ImpactRecord",
      "@azure/arm-postgresql-flexible!ObjectRecommendationDetails:interface": "Microsoft.DBforPostgreSQL.ObjectRecommendationDetails",
      "@azure/arm-postgresql-flexible!CheckNameAvailabilityRequest:interface": "Azure.ResourceManager.CommonTypes.CheckNameAvailabilityRequest",
      "@azure/arm-postgresql-flexible!NameAvailabilityModel:interface": "Microsoft.DBforPostgreSQL.NameAvailabilityModel",
      "@azure/arm-postgresql-flexible!CheckNameAvailabilityResponse:interface": "Azure.ResourceManager.CommonTypes.CheckNameAvailabilityResponse",
      "@azure/arm-postgresql-flexible!QuotaUsageList:interface": "Microsoft.DBforPostgreSQL.QuotaUsageList",
      "@azure/arm-postgresql-flexible!QuotaUsage:interface": "Microsoft.DBforPostgreSQL.QuotaUsage",
      "@azure/arm-postgresql-flexible!NameProperty:interface": "Microsoft.DBforPostgreSQL.NameProperty",
      "@azure/arm-postgresql-flexible!VirtualNetworkSubnetUsageParameter:interface": "Microsoft.DBforPostgreSQL.VirtualNetworkSubnetUsageParameter",
      "@azure/arm-postgresql-flexible!VirtualNetworkSubnetUsageModel:interface": "Microsoft.DBforPostgreSQL.VirtualNetworkSubnetUsageModel",
      "@azure/arm-postgresql-flexible!DelegatedSubnetUsage:interface": "Microsoft.DBforPostgreSQL.DelegatedSubnetUsage",
      "@azure/arm-postgresql-flexible!KnownOperationOrigin:enum": "Microsoft.DBforPostgreSQL.OperationOrigin",
      "@azure/arm-postgresql-flexible!KnownMigrationState:enum": "Microsoft.DBforPostgreSQL.MigrationState",
      "@azure/arm-postgresql-flexible!KnownMigrationSubstate:enum": "Microsoft.DBforPostgreSQL.MigrationSubstate",
      "@azure/arm-postgresql-flexible!KnownMigrationDatabaseState:enum": "Microsoft.DBforPostgreSQL.MigrationDatabaseState",
      "@azure/arm-postgresql-flexible!KnownValidationState:enum": "Microsoft.DBforPostgreSQL.ValidationState",
      "@azure/arm-postgresql-flexible!KnownMigrationMode:enum": "Microsoft.DBforPostgreSQL.MigrationMode",
      "@azure/arm-postgresql-flexible!KnownMigrationOption:enum": "Microsoft.DBforPostgreSQL.MigrationOption",
      "@azure/arm-postgresql-flexible!KnownSourceType:enum": "Microsoft.DBforPostgreSQL.SourceType",
      "@azure/arm-postgresql-flexible!KnownSslMode:enum": "Microsoft.DBforPostgreSQL.SslMode",
      "@azure/arm-postgresql-flexible!KnownSkuTier:enum": "Microsoft.DBforPostgreSQL.SkuTier",
      "@azure/arm-postgresql-flexible!KnownLogicalReplicationOnSourceServer:enum": "Microsoft.DBforPostgreSQL.LogicalReplicationOnSourceServer",
      "@azure/arm-postgresql-flexible!KnownOverwriteDatabasesOnTargetServer:enum": "Microsoft.DBforPostgreSQL.OverwriteDatabasesOnTargetServer",
      "@azure/arm-postgresql-flexible!KnownMigrateRolesAndPermissions:enum": "Microsoft.DBforPostgreSQL.MigrateRolesAndPermissions",
      "@azure/arm-postgresql-flexible!KnownStartDataMigration:enum": "Microsoft.DBforPostgreSQL.StartDataMigration",
      "@azure/arm-postgresql-flexible!KnownTriggerCutover:enum": "Microsoft.DBforPostgreSQL.TriggerCutover",
      "@azure/arm-postgresql-flexible!KnownCancel:enum": "Microsoft.DBforPostgreSQL.Cancel",
      "@azure/arm-postgresql-flexible!KnowncreatedByType:enum": "Azure.ResourceManager.CommonTypes.createdByType",
      "@azure/arm-postgresql-flexible!KnownMigrationListFilter:enum": "Microsoft.DBforPostgreSQL.MigrationListFilter",
      "@azure/arm-postgresql-flexible!KnownMigrationNameAvailabilityReason:enum": "Microsoft.DBforPostgreSQL.MigrationNameAvailabilityReason",
      "@azure/arm-postgresql-flexible!KnownPostgresMajorVersion:enum": "Microsoft.DBforPostgreSQL.PostgresMajorVersion",
      "@azure/arm-postgresql-flexible!KnownServerState:enum": "Microsoft.DBforPostgreSQL.ServerState",
      "@azure/arm-postgresql-flexible!KnownStorageAutoGrow:enum": "Microsoft.DBforPostgreSQL.StorageAutoGrow",
      "@azure/arm-postgresql-flexible!KnownAzureManagedDiskPerformanceTier:enum": "Microsoft.DBforPostgreSQL.AzureManagedDiskPerformanceTier",
      "@azure/arm-postgresql-flexible!KnownStorageType:enum": "Microsoft.DBforPostgreSQL.StorageType",
      "@azure/arm-postgresql-flexible!KnownMicrosoftEntraAuth:enum": "Microsoft.DBforPostgreSQL.MicrosoftEntraAuth",
      "@azure/arm-postgresql-flexible!KnownPasswordBasedAuth:enum": "Microsoft.DBforPostgreSQL.PasswordBasedAuth",
      "@azure/arm-postgresql-flexible!KnownDataEncryptionType:enum": "Microsoft.DBforPostgreSQL.DataEncryptionType",
      "@azure/arm-postgresql-flexible!KnownEncryptionKeyStatus:enum": "Microsoft.DBforPostgreSQL.EncryptionKeyStatus",
      "@azure/arm-postgresql-flexible!KnownGeographicallyRedundantBackup:enum": "Microsoft.DBforPostgreSQL.GeographicallyRedundantBackup",
      "@azure/arm-postgresql-flexible!KnownServerPublicNetworkAccessState:enum": "Microsoft.DBforPostgreSQL.ServerPublicNetworkAccessState",
      "@azure/arm-postgresql-flexible!KnownPostgreSqlFlexibleServerHighAvailabilityMode:enum": "Microsoft.DBforPostgreSQL.PostgreSqlFlexibleServerHighAvailabilityMode",
      "@azure/arm-postgresql-flexible!KnownHighAvailabilityState:enum": "Microsoft.DBforPostgreSQL.HighAvailabilityState",
      "@azure/arm-postgresql-flexible!KnownReplicationRole:enum": "Microsoft.DBforPostgreSQL.ReplicationRole",
      "@azure/arm-postgresql-flexible!KnownReplicationState:enum": "Microsoft.DBforPostgreSQL.ReplicationState",
      "@azure/arm-postgresql-flexible!KnownReadReplicaPromoteMode:enum": "Microsoft.DBforPostgreSQL.ReadReplicaPromoteMode",
      "@azure/arm-postgresql-flexible!KnownReadReplicaPromoteOption:enum": "Microsoft.DBforPostgreSQL.ReadReplicaPromoteOption",
      "@azure/arm-postgresql-flexible!KnownCreateMode:enum": "Microsoft.DBforPostgreSQL.CreateMode",
      "@azure/arm-postgresql-flexible!KnownPrivateEndpointServiceConnectionStatus:enum": "Azure.ResourceManager.CommonTypes.PrivateEndpointServiceConnectionStatus",
      "@azure/arm-postgresql-flexible!KnownPrivateEndpointConnectionProvisioningState:enum": "Azure.ResourceManager.CommonTypes.PrivateEndpointConnectionProvisioningState",
      "@azure/arm-postgresql-flexible!KnownIdentityType:enum": "Microsoft.DBforPostgreSQL.IdentityType",
      "@azure/arm-postgresql-flexible!KnownResourceProvisioningState:enum": "Azure.ResourceManager.ResourceProvisioningState",
      "@azure/arm-postgresql-flexible!KnownCreateModeForPatch:enum": "Microsoft.DBforPostgreSQL.CreateModeForPatch",
      "@azure/arm-postgresql-flexible!KnownFailoverMode:enum": "Microsoft.DBforPostgreSQL.FailoverMode",
      "@azure/arm-postgresql-flexible!KnownNetworkMigrationState:enum": "Microsoft.DBforPostgreSQL.NetworkMigrationState",
      "@azure/arm-postgresql-flexible!KnownConfigurationDataType:enum": "Microsoft.DBforPostgreSQL.ConfigurationDataType",
      "@azure/arm-postgresql-flexible!KnownVirtualEndpointType:enum": "Microsoft.DBforPostgreSQL.VirtualEndpointType",
      "@azure/arm-postgresql-flexible!KnownPrincipalType:enum": "Microsoft.DBforPostgreSQL.PrincipalType",
      "@azure/arm-postgresql-flexible!KnownCapabilityStatus:enum": "Microsoft.DBforPostgreSQL.CapabilityStatus",
      "@azure/arm-postgresql-flexible!KnownHighAvailabilityMode:enum": "Microsoft.DBforPostgreSQL.HighAvailabilityMode",
      "@azure/arm-postgresql-flexible!KnownFeatureStatus:enum": "Microsoft.DBforPostgreSQL.FeatureStatus",
      "@azure/arm-postgresql-flexible!KnownFastProvisioningSupport:enum": "Microsoft.DBforPostgreSQL.FastProvisioningSupport",
      "@azure/arm-postgresql-flexible!KnownGeographicallyRedundantBackupSupport:enum": "Microsoft.DBforPostgreSQL.GeographicallyRedundantBackupSupport",
      "@azure/arm-postgresql-flexible!KnownZoneRedundantHighAvailabilitySupport:enum": "Microsoft.DBforPostgreSQL.ZoneRedundantHighAvailabilitySupport",
      "@azure/arm-postgresql-flexible!KnownZoneRedundantHighAvailabilityAndGeographicallyRedundantBackupSupport:enum": "Microsoft.DBforPostgreSQL.ZoneRedundantHighAvailabilityAndGeographicallyRedundantBackupSupport",
      "@azure/arm-postgresql-flexible!KnownStorageAutoGrowthSupport:enum": "Microsoft.DBforPostgreSQL.StorageAutoGrowthSupport",
      "@azure/arm-postgresql-flexible!KnownOnlineStorageResizeSupport:enum": "Microsoft.DBforPostgreSQL.OnlineStorageResizeSupport",
      "@azure/arm-postgresql-flexible!KnownLocationRestricted:enum": "Microsoft.DBforPostgreSQL.LocationRestricted",
      "@azure/arm-postgresql-flexible!KnownExecutionStatus:enum": "Microsoft.DBforPostgreSQL.ExecutionStatus",
      "@azure/arm-postgresql-flexible!KnownThreatProtectionName:enum": "Microsoft.DBforPostgreSQL.ThreatProtectionName",
      "@azure/arm-postgresql-flexible!KnownThreatProtectionState:enum": "Microsoft.DBforPostgreSQL.ThreatProtectionState",
      "@azure/arm-postgresql-flexible!KnownBackupType:enum": "Microsoft.DBforPostgreSQL.BackupType",
      "@azure/arm-postgresql-flexible!KnownTuningOptionParameterEnum:enum": "Microsoft.DBforPostgreSQL.TuningOptionParameterEnum",
      "@azure/arm-postgresql-flexible!KnownRecommendationTypeParameterEnum:enum": "Microsoft.DBforPostgreSQL.RecommendationTypeParameterEnum",
      "@azure/arm-postgresql-flexible!KnownRecommendationTypeEnum:enum": "Microsoft.DBforPostgreSQL.RecommendationTypeEnum",
      "@azure/arm-postgresql-flexible!KnownCheckNameAvailabilityReason:enum": "Azure.ResourceManager.CommonTypes.CheckNameAvailabilityReason",
      "@azure/arm-postgresql-flexible!KnownVersions:enum": "Microsoft.DBforPostgreSQL.Versions",
      "@azure/arm-postgresql-flexible!VirtualNetworkSubnetUsageOperations#list:member": "Microsoft.DBforPostgreSQL.VirtualNetworkSubnetUsageOperationGroup.list",
      "@azure/arm-postgresql-flexible!QuotaUsagesOperations#list:member": "Microsoft.DBforPostgreSQL.QuotaUsagesOperationGroup.list",
      "@azure/arm-postgresql-flexible!PrivateDnsZoneSuffixOperations#get:member": "Microsoft.DBforPostgreSQL.PrivateDnsZoneSuffixOperationGroup.get",
      "@azure/arm-postgresql-flexible!NameAvailabilityOperations#checkWithLocation:member": "Microsoft.DBforPostgreSQL.NameAvailabilityOperationGroup.checkWithLocation",
      "@azure/arm-postgresql-flexible!NameAvailabilityOperations#checkGlobally:member": "Microsoft.DBforPostgreSQL.NameAvailabilityOperationGroup.checkGlobally",
      "@azure/arm-postgresql-flexible!CapabilitiesByLocationOperations#list:member": "Microsoft.DBforPostgreSQL.CapabilitiesByLocationOperationGroup.list",
      "@azure/arm-postgresql-flexible!TuningOptionsOperations#listRecommendations:member": "Microsoft.DBforPostgreSQL.TuningOptionsOperationGroup.listRecommendations",
      "@azure/arm-postgresql-flexible!TuningOptionsOperations#listByServer:member": "Microsoft.DBforPostgreSQL.TuningOptionsOperationGroup.listByServer",
      "@azure/arm-postgresql-flexible!TuningOptionsOperations#get:member": "Microsoft.DBforPostgreSQL.TuningOptionsOperationGroup.get",
      "@azure/arm-postgresql-flexible!BackupsAutomaticAndOnDemandOperations#listByServer:member": "Microsoft.DBforPostgreSQL.BackupAutomaticAndOnDemands.listByServer",
      "@azure/arm-postgresql-flexible!BackupsAutomaticAndOnDemandOperations#delete:member": "Microsoft.DBforPostgreSQL.BackupAutomaticAndOnDemands.delete",
      "@azure/arm-postgresql-flexible!BackupsAutomaticAndOnDemandOperations#create:member": "Microsoft.DBforPostgreSQL.BackupAutomaticAndOnDemands.create",
      "@azure/arm-postgresql-flexible!BackupsAutomaticAndOnDemandOperations#get:member": "Microsoft.DBforPostgreSQL.BackupAutomaticAndOnDemands.get",
      "@azure/arm-postgresql-flexible!ServerThreatProtectionSettingsOperations#createOrUpdate:member": "Microsoft.DBforPostgreSQL.AdvancedThreatProtectionSettingsModels.createOrUpdate",
      "@azure/arm-postgresql-flexible!AdvancedThreatProtectionSettingsOperations#listByServer:member": "Microsoft.DBforPostgreSQL.AdvancedThreatProtectionSettingsModels.listByServer",
      "@azure/arm-postgresql-flexible!AdvancedThreatProtectionSettingsOperations#get:member": "Microsoft.DBforPostgreSQL.AdvancedThreatProtectionSettingsModels.get",
      "@azure/arm-postgresql-flexible!ReplicasOperations#ListByServer:member": "Microsoft.DBforPostgreSQL.Servers.replicasListByServer",
      "@azure/arm-postgresql-flexible!BackupsLongTermRetentionOperations#listByServer:member": "Microsoft.DBforPostgreSQL.BackupsLongTermRetentionOperations.listByServer",
      "@azure/arm-postgresql-flexible!BackupsLongTermRetentionOperations#get:member": "Microsoft.DBforPostgreSQL.BackupsLongTermRetentionOperations.get",
      "@azure/arm-postgresql-flexible!BackupsLongTermRetentionOperations#start:member": "Microsoft.DBforPostgreSQL.Servers.start",
      "@azure/arm-postgresql-flexible!BackupsLongTermRetentionOperations#checkPrerequisites:member": "Microsoft.DBforPostgreSQL.Servers.checkPrerequisites",
      "@azure/arm-postgresql-flexible!CapturedLogsOperations#listByServer:member": "Microsoft.DBforPostgreSQL.Servers.listByServer",
      "@azure/arm-postgresql-flexible!CapabilitiesByServerOperations#list:member": "Microsoft.DBforPostgreSQL.Servers.list",
      "@azure/arm-postgresql-flexible!AdministratorsMicrosoftEntraOperations#listByServer:member": "Microsoft.DBforPostgreSQL.AdministratorMicrosoftEntras.listByServer",
      "@azure/arm-postgresql-flexible!AdministratorsMicrosoftEntraOperations#delete:member": "Microsoft.DBforPostgreSQL.AdministratorMicrosoftEntras.delete",
      "@azure/arm-postgresql-flexible!AdministratorsMicrosoftEntraOperations#createOrUpdate:member": "Microsoft.DBforPostgreSQL.AdministratorMicrosoftEntras.createOrUpdate",
      "@azure/arm-postgresql-flexible!AdministratorsMicrosoftEntraOperations#get:member": "Microsoft.DBforPostgreSQL.AdministratorMicrosoftEntras.get",
      "@azure/arm-postgresql-flexible!VirtualEndpointsOperations#listByServer:member": "Microsoft.DBforPostgreSQL.VirtualEndpoints.listByServer",
      "@azure/arm-postgresql-flexible!VirtualEndpointsOperations#delete:member": "Microsoft.DBforPostgreSQL.VirtualEndpoints.delete",
      "@azure/arm-postgresql-flexible!VirtualEndpointsOperations#update:member": "Microsoft.DBforPostgreSQL.VirtualEndpoints.update",
      "@azure/arm-postgresql-flexible!VirtualEndpointsOperations#create:member": "Microsoft.DBforPostgreSQL.VirtualEndpoints.create",
      "@azure/arm-postgresql-flexible!VirtualEndpointsOperations#get:member": "Microsoft.DBforPostgreSQL.VirtualEndpoints.get",
      "@azure/arm-postgresql-flexible!PrivateLinkResourcesOperations#listByServer:member": "Microsoft.DBforPostgreSQL.PrivateLinkResources.listByServer",
      "@azure/arm-postgresql-flexible!PrivateLinkResourcesOperations#get:member": "Microsoft.DBforPostgreSQL.PrivateLinkResources.get",
      "@azure/arm-postgresql-flexible!PrivateEndpointConnectionsOperations#listByServer:member": "Microsoft.DBforPostgreSQL.PrivateEndpointConnections.listByServer",
      "@azure/arm-postgresql-flexible!PrivateEndpointConnectionsOperations#delete:member": "Microsoft.DBforPostgreSQL.PrivateEndpointConnections.delete",
      "@azure/arm-postgresql-flexible!PrivateEndpointConnectionsOperations#update:member": "Microsoft.DBforPostgreSQL.PrivateEndpointConnections.update",
      "@azure/arm-postgresql-flexible!PrivateEndpointConnectionsOperations#get:member": "Microsoft.DBforPostgreSQL.PrivateEndpointConnections.get",
      "@azure/arm-postgresql-flexible!FirewallRulesOperations#listByServer:member": "Microsoft.DBforPostgreSQL.FirewallRules.listByServer",
      "@azure/arm-postgresql-flexible!FirewallRulesOperations#delete:member": "Microsoft.DBforPostgreSQL.FirewallRules.delete",
      "@azure/arm-postgresql-flexible!FirewallRulesOperations#createOrUpdate:member": "Microsoft.DBforPostgreSQL.FirewallRules.createOrUpdate",
      "@azure/arm-postgresql-flexible!FirewallRulesOperations#get:member": "Microsoft.DBforPostgreSQL.FirewallRules.get",
      "@azure/arm-postgresql-flexible!DatabasesOperations#listByServer:member": "Microsoft.DBforPostgreSQL.Databases.listByServer",
      "@azure/arm-postgresql-flexible!DatabasesOperations#delete:member": "Microsoft.DBforPostgreSQL.Databases.delete",
      "@azure/arm-postgresql-flexible!DatabasesOperations#create:member": "Microsoft.DBforPostgreSQL.Databases.create",
      "@azure/arm-postgresql-flexible!DatabasesOperations#get:member": "Microsoft.DBforPostgreSQL.Databases.get",
      "@azure/arm-postgresql-flexible!ConfigurationsOperations#listByServer:member": "Microsoft.DBforPostgreSQL.Configurations.listByServer",
      "@azure/arm-postgresql-flexible!ConfigurationsOperations#update:member": "Microsoft.DBforPostgreSQL.Configurations.update",
      "@azure/arm-postgresql-flexible!ConfigurationsOperations#put:member": "Microsoft.DBforPostgreSQL.Configurations.put",
      "@azure/arm-postgresql-flexible!ConfigurationsOperations#get:member": "Microsoft.DBforPostgreSQL.Configurations.get",
      "@azure/arm-postgresql-flexible!ServersOperations#migrateNetworkMode:member": "Microsoft.DBforPostgreSQL.Servers.migrateNetworkMode",
      "@azure/arm-postgresql-flexible!ServersOperations#stop:member": "Microsoft.DBforPostgreSQL.Servers.stop",
      "@azure/arm-postgresql-flexible!ServersOperations#Start:member": "Microsoft.DBforPostgreSQL.Servers.serversStart",
      "@azure/arm-postgresql-flexible!ServersOperations#restart:member": "Microsoft.DBforPostgreSQL.Servers.restart",
      "@azure/arm-postgresql-flexible!ServersOperations#listBySubscription:member": "Microsoft.DBforPostgreSQL.Servers.listBySubscription",
      "@azure/arm-postgresql-flexible!ServersOperations#listByResourceGroup:member": "Microsoft.DBforPostgreSQL.Servers.listByResourceGroup",
      "@azure/arm-postgresql-flexible!ServersOperations#delete:member": "Microsoft.DBforPostgreSQL.Servers.delete",
      "@azure/arm-postgresql-flexible!ServersOperations#update:member": "Microsoft.DBforPostgreSQL.Servers.update",
      "@azure/arm-postgresql-flexible!ServersOperations#createOrUpdate:member": "Microsoft.DBforPostgreSQL.Servers.createOrUpdate",
      "@azure/arm-postgresql-flexible!ServersOperations#get:member": "Microsoft.DBforPostgreSQL.Servers.get",
      "@azure/arm-postgresql-flexible!MigrationsOperations#checkNameAvailability:member": "Microsoft.DBforPostgreSQL.Servers.checkNameAvailability",
      "@azure/arm-postgresql-flexible!MigrationsOperations#listByTargetServer:member": "Microsoft.DBforPostgreSQL.Migrations.listByTargetServer",
      "@azure/arm-postgresql-flexible!MigrationsOperations#cancel:member": "Microsoft.DBforPostgreSQL.Migrations.cancel",
      "@azure/arm-postgresql-flexible!MigrationsOperations#update:member": "Microsoft.DBforPostgreSQL.Migrations.update",
      "@azure/arm-postgresql-flexible!MigrationsOperations#create:member": "Microsoft.DBforPostgreSQL.Migrations.create",
      "@azure/arm-postgresql-flexible!MigrationsOperations#get:member": "Microsoft.DBforPostgreSQL.Migrations.get",
      "@azure/arm-postgresql-flexible!OperationsOperations#list:member": "Azure.ResourceManager.Legacy.Operations.list"
    }
  }
}
