{
  "apiVersion": "2025-10-01-preview",
  "emitterVersion": "0.48.1",
  "crossLanguageDefinitions": {
    "CrossLanguagePackageId": "Microsoft.EdgeMarketplace",
    "CrossLanguageDefinitionId": {
      "@azure/arm-edgemarketplace!OperationListResult:interface": "Azure.ResourceManager.CommonTypes.OperationListResult",
      "@azure/arm-edgemarketplace!Operation:interface": "Azure.ResourceManager.CommonTypes.Operation",
      "@azure/arm-edgemarketplace!OperationDisplay:interface": "Azure.ResourceManager.CommonTypes.OperationDisplay",
      "@azure/arm-edgemarketplace!ErrorResponse:interface": "Azure.ResourceManager.CommonTypes.ErrorResponse",
      "@azure/arm-edgemarketplace!ErrorDetail:interface": "Azure.ResourceManager.CommonTypes.ErrorDetail",
      "@azure/arm-edgemarketplace!ErrorAdditionalInfo:interface": "Azure.ResourceManager.CommonTypes.ErrorAdditionalInfo",
      "@azure/arm-edgemarketplace!Offer:interface": "Microsoft.EdgeMarketplace.Offer",
      "@azure/arm-edgemarketplace!OfferProperties:interface": "Microsoft.EdgeMarketplace.OfferProperties",
      "@azure/arm-edgemarketplace!OfferContent:interface": "Microsoft.EdgeMarketplace.OfferContent",
      "@azure/arm-edgemarketplace!OfferPublisher:interface": "Microsoft.EdgeMarketplace.OfferPublisher",
      "@azure/arm-edgemarketplace!IconFileUris:interface": "Microsoft.EdgeMarketplace.IconFileUris",
      "@azure/arm-edgemarketplace!TermsAndConditions:interface": "Microsoft.EdgeMarketplace.TermsAndConditions",
      "@azure/arm-edgemarketplace!MarketplaceSku:interface": "Microsoft.EdgeMarketplace.MarketplaceSku",
      "@azure/arm-edgemarketplace!SkuOperatingSystem:interface": "Microsoft.EdgeMarketplace.SkuOperatingSystem",
      "@azure/arm-edgemarketplace!MarketplaceSkuVersion:interface": "Microsoft.EdgeMarketplace.MarketplaceSkuVersion",
      "@azure/arm-edgemarketplace!ExtensionResource:interface": "Azure.ResourceManager.CommonTypes.ExtensionResource",
      "@azure/arm-edgemarketplace!Resource:interface": "Azure.ResourceManager.CommonTypes.Resource",
      "@azure/arm-edgemarketplace!SystemData:interface": "Azure.ResourceManager.CommonTypes.SystemData",
      "@azure/arm-edgemarketplace!OfferListResult:interface": "Azure.ResourceManager.ResourceListResult",
      "@azure/arm-edgemarketplace!AccessTokenRequest:interface": "Microsoft.EdgeMarketplace.AccessTokenRequest",
      "@azure/arm-edgemarketplace!DiskAccessToken:interface": "Microsoft.EdgeMarketplace.DiskAccessToken",
      "@azure/arm-edgemarketplace!ArmOperationStatusResourceProvisioningState:interface": "Azure.ResourceManager.ArmOperationStatus",
      "@azure/arm-edgemarketplace!AccessTokenReadRequest:interface": "Microsoft.EdgeMarketplace.AccessTokenReadRequest",
      "@azure/arm-edgemarketplace!Publisher:interface": "Microsoft.EdgeMarketplace.Publisher",
      "@azure/arm-edgemarketplace!PublisherProperties:interface": "Microsoft.EdgeMarketplace.PublisherProperties",
      "@azure/arm-edgemarketplace!PublisherListResult:interface": "Azure.ResourceManager.ResourceListResult",
      "@azure/arm-edgemarketplace!KnownOrigin:enum": "Azure.ResourceManager.CommonTypes.Origin",
      "@azure/arm-edgemarketplace!KnownActionType:enum": "Azure.ResourceManager.CommonTypes.ActionType",
      "@azure/arm-edgemarketplace!KnownOfferAvailability:enum": "Microsoft.EdgeMarketplace.OfferAvailability",
      "@azure/arm-edgemarketplace!KnownOfferReleaseType:enum": "Microsoft.EdgeMarketplace.OfferReleaseType",
      "@azure/arm-edgemarketplace!KnownResourceProvisioningState:enum": "Azure.ResourceManager.ResourceProvisioningState",
      "@azure/arm-edgemarketplace!KnownOfferLaunchType:enum": "Microsoft.EdgeMarketplace.OfferLaunchType",
      "@azure/arm-edgemarketplace!KnowncreatedByType:enum": "Azure.ResourceManager.CommonTypes.createdByType",
      "@azure/arm-edgemarketplace!KnownVersions:enum": "Microsoft.EdgeMarketplace.Versions",
      "@azure/arm-edgemarketplace!PublishersOperations#listBySubscription:member": "Microsoft.EdgeMarketplace.Publishers.listBySubscription",
      "@azure/arm-edgemarketplace!PublishersOperations#list:member": "Microsoft.EdgeMarketplace.Publishers.list",
      "@azure/arm-edgemarketplace!PublishersOperations#get:member": "Microsoft.EdgeMarketplace.Publishers.get",
      "@azure/arm-edgemarketplace!OffersOperations#listBySubscription:member": "Microsoft.EdgeMarketplace.Offers.listBySubscription",
      "@azure/arm-edgemarketplace!OffersOperations#getAccessToken:member": "Microsoft.EdgeMarketplace.Offers.getAccessToken",
      "@azure/arm-edgemarketplace!OffersOperations#generateAccessToken:member": "Microsoft.EdgeMarketplace.Offers.generateAccessToken",
      "@azure/arm-edgemarketplace!OffersOperations#list:member": "Microsoft.EdgeMarketplace.Offers.list",
      "@azure/arm-edgemarketplace!OffersOperations#get:member": "Microsoft.EdgeMarketplace.Offers.get",
      "@azure/arm-edgemarketplace!OperationsOperations#list:member": "Azure.ResourceManager.Operations.list"
    }
  }
}
