{
  "apiVersion": "2025-01-02",
  "emitterVersion": "0.46.1",
  "crossLanguageDefinitions": {
    "CrossLanguagePackageId": "Microsoft.Compute",
    "CrossLanguageDefinitionId": {
      "@azure/arm-compute-disk!Disk:interface": "Microsoft.Compute.Disk",
      "@azure/arm-compute-disk!DiskProperties:interface": "Microsoft.Compute.DiskProperties",
      "@azure/arm-compute-disk!DiskPurchasePlan:interface": "Microsoft.Compute.DiskPurchasePlan",
      "@azure/arm-compute-disk!SupportedCapabilities:interface": "Microsoft.Compute.SupportedCapabilities",
      "@azure/arm-compute-disk!CreationData:interface": "Microsoft.Compute.CreationData",
      "@azure/arm-compute-disk!ImageDiskReference:interface": "Microsoft.Compute.ImageDiskReference",
      "@azure/arm-compute-disk!EncryptionSettingsCollection:interface": "Microsoft.Compute.EncryptionSettingsCollection",
      "@azure/arm-compute-disk!EncryptionSettingsElement:interface": "Microsoft.Compute.EncryptionSettingsElement",
      "@azure/arm-compute-disk!KeyVaultAndSecretReference:interface": "Microsoft.Compute.KeyVaultAndSecretReference",
      "@azure/arm-compute-disk!SourceVault:interface": "Microsoft.Compute.SourceVault",
      "@azure/arm-compute-disk!KeyVaultAndKeyReference:interface": "Microsoft.Compute.KeyVaultAndKeyReference",
      "@azure/arm-compute-disk!Encryption:interface": "Microsoft.Compute.Encryption",
      "@azure/arm-compute-disk!ShareInfoElement:interface": "Microsoft.Compute.ShareInfoElement",
      "@azure/arm-compute-disk!PropertyUpdatesInProgress:interface": "Microsoft.Compute.PropertyUpdatesInProgress",
      "@azure/arm-compute-disk!DiskSecurityProfile:interface": "Microsoft.Compute.DiskSecurityProfile",
      "@azure/arm-compute-disk!AvailabilityPolicy:interface": "Microsoft.Compute.AvailabilityPolicy",
      "@azure/arm-compute-disk!DiskSku:interface": "Microsoft.Compute.DiskSku",
      "@azure/arm-compute-disk!ExtendedLocation:interface": "Microsoft.Compute.ExtendedLocation",
      "@azure/arm-compute-disk!TrackedResource:interface": "Azure.ResourceManager.CommonTypes.TrackedResource",
      "@azure/arm-compute-disk!Resource:interface": "Azure.ResourceManager.CommonTypes.Resource",
      "@azure/arm-compute-disk!SystemData:interface": "Azure.ResourceManager.CommonTypes.SystemData",
      "@azure/arm-compute-disk!CloudError:interface": "Microsoft.Compute.CloudError",
      "@azure/arm-compute-disk!ApiError:interface": "Microsoft.Compute.ApiError",
      "@azure/arm-compute-disk!ApiErrorBase:interface": "Microsoft.Compute.ApiErrorBase",
      "@azure/arm-compute-disk!InnerError:interface": "Microsoft.Compute.InnerError",
      "@azure/arm-compute-disk!ArmOperationStatusResourceProvisioningState:interface": "Azure.ResourceManager.ArmOperationStatus",
      "@azure/arm-compute-disk!ErrorDetail:interface": "Azure.ResourceManager.CommonTypes.ErrorDetail",
      "@azure/arm-compute-disk!ErrorAdditionalInfo:interface": "Azure.ResourceManager.CommonTypes.ErrorAdditionalInfo",
      "@azure/arm-compute-disk!DiskUpdate:interface": "Microsoft.Compute.DiskUpdate",
      "@azure/arm-compute-disk!DiskUpdateProperties:interface": "Microsoft.Compute.DiskUpdateProperties",
      "@azure/arm-compute-disk!DiskList:interface": "Microsoft.Compute.DiskList",
      "@azure/arm-compute-disk!GrantAccessData:interface": "Microsoft.Compute.GrantAccessData",
      "@azure/arm-compute-disk!AccessUri:interface": "Microsoft.Compute.AccessUri",
      "@azure/arm-compute-disk!DiskAccess:interface": "Microsoft.Compute.DiskAccess",
      "@azure/arm-compute-disk!DiskAccessProperties:interface": "Microsoft.Compute.DiskAccessProperties",
      "@azure/arm-compute-disk!PrivateEndpointConnection:interface": "Microsoft.Compute.PrivateEndpointConnection",
      "@azure/arm-compute-disk!PrivateEndpointConnectionProperties:interface": "Microsoft.Compute.PrivateEndpointConnectionProperties",
      "@azure/arm-compute-disk!PrivateEndpoint:interface": "Microsoft.Compute.PrivateEndpoint",
      "@azure/arm-compute-disk!PrivateLinkServiceConnectionState:interface": "Microsoft.Compute.PrivateLinkServiceConnectionState",
      "@azure/arm-compute-disk!ProxyResource:interface": "Azure.ResourceManager.CommonTypes.ProxyResource",
      "@azure/arm-compute-disk!DiskAccessUpdate:interface": "Microsoft.Compute.DiskAccessUpdate",
      "@azure/arm-compute-disk!DiskAccessList:interface": "Microsoft.Compute.DiskAccessList",
      "@azure/arm-compute-disk!PrivateLinkResourceListResult:interface": "Microsoft.Compute.PrivateLinkResourceListResult",
      "@azure/arm-compute-disk!PrivateLinkResource:interface": "Microsoft.Compute.PrivateLinkResource",
      "@azure/arm-compute-disk!PrivateLinkResourceProperties:interface": "Microsoft.Compute.PrivateLinkResourceProperties",
      "@azure/arm-compute-disk!PrivateEndpointConnectionListResult:interface": "Microsoft.Compute.PrivateEndpointConnectionListResult",
      "@azure/arm-compute-disk!DiskEncryptionSet:interface": "Microsoft.Compute.DiskEncryptionSet",
      "@azure/arm-compute-disk!EncryptionSetProperties:interface": "Microsoft.Compute.EncryptionSetProperties",
      "@azure/arm-compute-disk!KeyForDiskEncryptionSet:interface": "Microsoft.Compute.KeyForDiskEncryptionSet",
      "@azure/arm-compute-disk!EncryptionSetIdentity:interface": "Microsoft.Compute.EncryptionSetIdentity",
      "@azure/arm-compute-disk!UserAssignedIdentitiesValue:interface": "Microsoft.Compute.UserAssignedIdentitiesValue",
      "@azure/arm-compute-disk!DiskEncryptionSetUpdate:interface": "Microsoft.Compute.DiskEncryptionSetUpdate",
      "@azure/arm-compute-disk!DiskEncryptionSetUpdateProperties:interface": "Microsoft.Compute.DiskEncryptionSetUpdateProperties",
      "@azure/arm-compute-disk!DiskEncryptionSetList:interface": "Microsoft.Compute.DiskEncryptionSetList",
      "@azure/arm-compute-disk!ResourceUriList:interface": "Microsoft.Compute.ResourceUriList",
      "@azure/arm-compute-disk!Snapshot:interface": "Microsoft.Compute.Snapshot",
      "@azure/arm-compute-disk!SnapshotProperties:interface": "Microsoft.Compute.SnapshotProperties",
      "@azure/arm-compute-disk!CopyCompletionError:interface": "Microsoft.Compute.CopyCompletionError",
      "@azure/arm-compute-disk!SnapshotSku:interface": "Microsoft.Compute.SnapshotSku",
      "@azure/arm-compute-disk!SnapshotUpdate:interface": "Microsoft.Compute.SnapshotUpdate",
      "@azure/arm-compute-disk!SnapshotUpdateProperties:interface": "Microsoft.Compute.SnapshotUpdateProperties",
      "@azure/arm-compute-disk!SnapshotList:interface": "Microsoft.Compute.SnapshotList",
      "@azure/arm-compute-disk!DiskRestorePoint:interface": "Microsoft.Compute.DiskRestorePoint",
      "@azure/arm-compute-disk!DiskRestorePointProperties:interface": "Microsoft.Compute.DiskRestorePointProperties",
      "@azure/arm-compute-disk!DiskRestorePointList:interface": "Microsoft.Compute.DiskRestorePointList",
      "@azure/arm-compute-disk!KnownOperatingSystemTypes:enum": "Microsoft.Compute.OperatingSystemTypes",
      "@azure/arm-compute-disk!KnownHyperVGeneration:enum": "Microsoft.Compute.HyperVGeneration",
      "@azure/arm-compute-disk!KnownArchitecture:enum": "Microsoft.Compute.Architecture",
      "@azure/arm-compute-disk!KnownSupportedSecurityOption:enum": "Microsoft.Compute.SupportedSecurityOption",
      "@azure/arm-compute-disk!KnownDiskCreateOption:enum": "Microsoft.Compute.DiskCreateOption",
      "@azure/arm-compute-disk!KnownProvisionedBandwidthCopyOption:enum": "Microsoft.Compute.ProvisionedBandwidthCopyOption",
      "@azure/arm-compute-disk!KnownDiskState:enum": "Microsoft.Compute.DiskState",
      "@azure/arm-compute-disk!KnownEncryptionType:enum": "Microsoft.Compute.EncryptionType",
      "@azure/arm-compute-disk!KnownNetworkAccessPolicy:enum": "Microsoft.Compute.NetworkAccessPolicy",
      "@azure/arm-compute-disk!KnownDiskSecurityTypes:enum": "Microsoft.Compute.DiskSecurityTypes",
      "@azure/arm-compute-disk!KnownPublicNetworkAccess:enum": "Microsoft.Compute.PublicNetworkAccess",
      "@azure/arm-compute-disk!KnownDataAccessAuthMode:enum": "Microsoft.Compute.DataAccessAuthMode",
      "@azure/arm-compute-disk!KnownAvailabilityPolicyDiskDelay:enum": "Microsoft.Compute.AvailabilityPolicyDiskDelay",
      "@azure/arm-compute-disk!KnownDiskStorageAccountTypes:enum": "Microsoft.Compute.DiskStorageAccountTypes",
      "@azure/arm-compute-disk!KnownExtendedLocationTypes:enum": "Microsoft.Compute.ExtendedLocationTypes",
      "@azure/arm-compute-disk!KnowncreatedByType:enum": "Azure.ResourceManager.CommonTypes.createdByType",
      "@azure/arm-compute-disk!KnownResourceProvisioningState:enum": "Azure.ResourceManager.ResourceProvisioningState",
      "@azure/arm-compute-disk!KnownAccessLevel:enum": "Microsoft.Compute.AccessLevel",
      "@azure/arm-compute-disk!KnownFileFormat:enum": "Microsoft.Compute.FileFormat",
      "@azure/arm-compute-disk!KnownPrivateEndpointServiceConnectionStatus:enum": "Microsoft.Compute.PrivateEndpointServiceConnectionStatus",
      "@azure/arm-compute-disk!KnownPrivateEndpointConnectionProvisioningState:enum": "Microsoft.Compute.PrivateEndpointConnectionProvisioningState",
      "@azure/arm-compute-disk!KnownDiskEncryptionSetType:enum": "Microsoft.Compute.DiskEncryptionSetType",
      "@azure/arm-compute-disk!KnownDiskEncryptionSetIdentityType:enum": "Microsoft.Compute.DiskEncryptionSetIdentityType",
      "@azure/arm-compute-disk!KnownCopyCompletionErrorReason:enum": "Microsoft.Compute.CopyCompletionErrorReason",
      "@azure/arm-compute-disk!KnownSnapshotAccessState:enum": "Microsoft.Compute.SnapshotAccessState",
      "@azure/arm-compute-disk!KnownSnapshotStorageAccountTypes:enum": "Microsoft.Compute.SnapshotStorageAccountTypes",
      "@azure/arm-compute-disk!KnownVersions:enum": "Microsoft.Compute.Versions",
      "@azure/arm-compute-disk!DiskRestorePointOperations#revokeAccess:member": "Microsoft.Compute.DiskRestorePoints.revokeAccess",
      "@azure/arm-compute-disk!DiskRestorePointOperations#grantAccess:member": "Microsoft.Compute.DiskRestorePoints.grantAccess",
      "@azure/arm-compute-disk!DiskRestorePointOperations#listByRestorePoint:member": "Microsoft.Compute.DiskRestorePoints.listByRestorePoint",
      "@azure/arm-compute-disk!DiskRestorePointOperations#get:member": "Microsoft.Compute.DiskRestorePoints.get",
      "@azure/arm-compute-disk!SnapshotsOperations#revokeAccess:member": "Microsoft.Compute.Snapshots.revokeAccess",
      "@azure/arm-compute-disk!SnapshotsOperations#grantAccess:member": "Microsoft.Compute.Snapshots.grantAccess",
      "@azure/arm-compute-disk!SnapshotsOperations#list:member": "Microsoft.Compute.Snapshots.list",
      "@azure/arm-compute-disk!SnapshotsOperations#listByResourceGroup:member": "Microsoft.Compute.Snapshots.listByResourceGroup",
      "@azure/arm-compute-disk!SnapshotsOperations#delete:member": "Microsoft.Compute.Snapshots.delete",
      "@azure/arm-compute-disk!SnapshotsOperations#update:member": "Microsoft.Compute.Snapshots.update",
      "@azure/arm-compute-disk!SnapshotsOperations#createOrUpdate:member": "Microsoft.Compute.Snapshots.createOrUpdate",
      "@azure/arm-compute-disk!SnapshotsOperations#get:member": "Microsoft.Compute.Snapshots.get",
      "@azure/arm-compute-disk!DiskEncryptionSetsOperations#listAssociatedResources:member": "Microsoft.Compute.DiskEncryptionSets.listAssociatedResources",
      "@azure/arm-compute-disk!DiskEncryptionSetsOperations#list:member": "Microsoft.Compute.DiskEncryptionSets.list",
      "@azure/arm-compute-disk!DiskEncryptionSetsOperations#listByResourceGroup:member": "Microsoft.Compute.DiskEncryptionSets.listByResourceGroup",
      "@azure/arm-compute-disk!DiskEncryptionSetsOperations#delete:member": "Microsoft.Compute.DiskEncryptionSets.delete",
      "@azure/arm-compute-disk!DiskEncryptionSetsOperations#update:member": "Microsoft.Compute.DiskEncryptionSets.update",
      "@azure/arm-compute-disk!DiskEncryptionSetsOperations#createOrUpdate:member": "Microsoft.Compute.DiskEncryptionSets.createOrUpdate",
      "@azure/arm-compute-disk!DiskEncryptionSetsOperations#get:member": "Microsoft.Compute.DiskEncryptionSets.get",
      "@azure/arm-compute-disk!DiskAccessesOperations#listPrivateEndpointConnections:member": "Microsoft.Compute.PrivateEndpointConnections.listPrivateEndpointConnections",
      "@azure/arm-compute-disk!DiskAccessesOperations#deleteAPrivateEndpointConnection:member": "Microsoft.Compute.PrivateEndpointConnections.deleteAPrivateEndpointConnection",
      "@azure/arm-compute-disk!DiskAccessesOperations#updateAPrivateEndpointConnection:member": "Microsoft.Compute.PrivateEndpointConnections.updateAPrivateEndpointConnection",
      "@azure/arm-compute-disk!DiskAccessesOperations#getAPrivateEndpointConnection:member": "Microsoft.Compute.PrivateEndpointConnections.getAPrivateEndpointConnection",
      "@azure/arm-compute-disk!DiskAccessesOperations#getPrivateLinkResources:member": "Microsoft.Compute.DiskAccesses.getPrivateLinkResources",
      "@azure/arm-compute-disk!DiskAccessesOperations#list:member": "Microsoft.Compute.DiskAccesses.list",
      "@azure/arm-compute-disk!DiskAccessesOperations#listByResourceGroup:member": "Microsoft.Compute.DiskAccesses.listByResourceGroup",
      "@azure/arm-compute-disk!DiskAccessesOperations#delete:member": "Microsoft.Compute.DiskAccesses.delete",
      "@azure/arm-compute-disk!DiskAccessesOperations#update:member": "Microsoft.Compute.DiskAccesses.update",
      "@azure/arm-compute-disk!DiskAccessesOperations#createOrUpdate:member": "Microsoft.Compute.DiskAccesses.createOrUpdate",
      "@azure/arm-compute-disk!DiskAccessesOperations#get:member": "Microsoft.Compute.DiskAccesses.get",
      "@azure/arm-compute-disk!DisksOperations#revokeAccess:member": "Microsoft.Compute.Disks.revokeAccess",
      "@azure/arm-compute-disk!DisksOperations#grantAccess:member": "Microsoft.Compute.Disks.grantAccess",
      "@azure/arm-compute-disk!DisksOperations#list:member": "Microsoft.Compute.Disks.list",
      "@azure/arm-compute-disk!DisksOperations#listByResourceGroup:member": "Microsoft.Compute.Disks.listByResourceGroup",
      "@azure/arm-compute-disk!DisksOperations#delete:member": "Microsoft.Compute.Disks.delete",
      "@azure/arm-compute-disk!DisksOperations#update:member": "Microsoft.Compute.Disks.update",
      "@azure/arm-compute-disk!DisksOperations#createOrUpdate:member": "Microsoft.Compute.Disks.createOrUpdate",
      "@azure/arm-compute-disk!DisksOperations#get:member": "Microsoft.Compute.Disks.get"
    }
  }
}
